pyexamgenerator/__init__.py
pyexamgenerator/exam_generator.py
pyexamgenerator/main_app.py
pyexamgenerator/question_bank_manager.py
pyexamgenerator/question_generator.py
pyexamgenerator/tooltip.py
pyexamgenerator-0.2.2.dist-info/licenses/LICENSE
pyexamgenerator-0.2.2.dist-info/METADATA
pyexamgenerator-0.2.2.dist-info/WHEEL
pyexamgenerator-0.2.2.dist-info/entry_points.txt
pyexamgenerator-0.2.2.dist-info/top_level.txt
pyexamgenerator-0.2.2.dist-info/RECORD
