Metadata-Version: 2.4
Name: pyexamgenerator
Version: 0.2.2
Summary: Una herramienta de escritorio para generar exámenes desde PDFs usando IA.
Home-page: https://github.com/dsanchez-garcia/pyexamgenerator
Author: Daniel Sánchez-García
Author-email: daniel.sanchezgarcia@uca.es
License: GPL-3.0-or-later
Keywords: exam,generator,ai,gemini,pdf,moodle,quiz,education,test
Classifier: Development Status :: 4 - Beta
Classifier: Intended Audience :: Education
Classifier: Intended Audience :: Developers
Classifier: Topic :: Education
Classifier: Topic :: Text Processing
Classifier: Topic :: Utilities
Classifier: Programming Language :: Python :: 3
Classifier: Programming Language :: Python :: 3.8
Classifier: Programming Language :: Python :: 3.9
Classifier: Programming Language :: Python :: 3.10
Classifier: Programming Language :: Python :: 3.11
Classifier: Programming Language :: Python :: 3.12
Classifier: Operating System :: OS Independent
Requires-Python: >=3.8
License-File: LICENSE
Requires-Dist: google-genai
Requires-Dist: PyPDF2
Requires-Dist: python-docx
Requires-Dist: pandas
Requires-Dist: openpyxl
Requires-Dist: ttkwidgets
Requires-Dist: importlib-metadata; python_version < "3.8"
Dynamic: author
Dynamic: author-email
Dynamic: classifier
Dynamic: description
Dynamic: description-content-type
Dynamic: home-page
Dynamic: keywords
Dynamic: license
Dynamic: license-file
Dynamic: requires-dist
Dynamic: requires-python
Dynamic: summary
